Metadata-Version: 1.0
Name: youtube-title-parser
Version: 0.1
Summary: Parse Youtube Title into Artist name and Song name
Home-page: https://github.com/MrCorncob/Youtube-Title-Parser.git
Author: Corncob
Author-email: daiyen@daiyen.info
License: GPL 3.0
Platform: UNKNOWN
